cdv/__init__.py
cdv/clibs/__init__.py
cdv/clibs/condition_codes.clib
cdv/clibs/curry_and_treehash.clib
cdv/clibs/sha256tree.clib
cdv/clibs/singleton_truths.clib
cdv/clibs/utility_macros.clib
cdv/cmds/__init__.py
cdv/cmds/chia_inspect.py
cdv/cmds/cli.py
cdv/cmds/clsp.py
cdv/cmds/rpc.py
cdv/cmds/sim.py
cdv/cmds/sim_utils.py
cdv/cmds/util.py
cdv/examples/__init__.py
cdv/examples/clsp/__init__.py
cdv/examples/clsp/piggybank.clsp
cdv/examples/clsp/piggybank.clsp.hex
cdv/examples/clvm/__init__.py
cdv/examples/drivers/__init__.py
cdv/examples/drivers/piggybank_drivers.py
cdv/test/__init__.py
cdv/test/test_skeleton.py
cdv/util/__init__.py
cdv/util/keys.py
cdv/util/load_clvm.py
chia_dev_tools-1.1.4.dist-info/LICENSE
chia_dev_tools-1.1.4.dist-info/METADATA
chia_dev_tools-1.1.4.dist-info/WHEEL
chia_dev_tools-1.1.4.dist-info/entry_points.txt
chia_dev_tools-1.1.4.dist-info/top_level.txt
chia_dev_tools-1.1.4.dist-info/RECORD
