Metadata-Version: 2.1
Name: chia-dev-tools
Version: 1.1.4
Summary: Chia development commands
Home-page: https://github.com/Chia-Network
Author: Quexington
Author-email: m.hauff@chia.net
License: https://opensource.org/licenses/Apache-2.0
Project-URL: Bug Reports, https://github.com/Chia-Network/chia-dev-tools
Project-URL: Source, https://github.com/Chia-Network/chia-dev-tools
Classifier: Programming Language :: Python :: 3
Classifier: Programming Language :: Python :: 3.8
Classifier: Programming Language :: Python :: 3.9
Classifier: License :: OSI Approved :: Apache Software License
Classifier: Topic :: Security :: Cryptography
License-File: LICENSE
Requires-Dist: chia-blockchain (==1.6.2)
Requires-Dist: packaging
Requires-Dist: pytest
Requires-Dist: pytest-asyncio
Requires-Dist: pytimeparse
Provides-Extra: dev
Requires-Dist: flake8 ; extra == 'dev'
Requires-Dist: mypy ; extra == 'dev'
Requires-Dist: types-aiofiles ; extra == 'dev'
Requires-Dist: types-click ; extra == 'dev'
Requires-Dist: types-cryptography ; extra == 'dev'
Requires-Dist: types-pkg-resources ; extra == 'dev'
Requires-Dist: types-pyyaml ; extra == 'dev'
Requires-Dist: types-setuptools ; extra == 'dev'
Requires-Dist: black (==21.12b0) ; extra == 'dev'
Requires-Dist: isort ; extra == 'dev'
Requires-Dist: pre-commit ; extra == 'dev'
Requires-Dist: pylint ; extra == 'dev'
